localstripe/__init__.py
localstripe/__main__.py
localstripe/errors.py
localstripe/localstripe-v3.js
localstripe/resources.py
localstripe/server.py
localstripe/webhooks.py
localstack_localstripe-1.15.6.post1.dist-info/LICENSE
localstack_localstripe-1.15.6.post1.dist-info/METADATA
localstack_localstripe-1.15.6.post1.dist-info/WHEEL
localstack_localstripe-1.15.6.post1.dist-info/entry_points.txt
localstack_localstripe-1.15.6.post1.dist-info/top_level.txt
localstack_localstripe-1.15.6.post1.dist-info/RECORD
